setup.py
socket.py
micropython_socket.egg-info/PKG-INFO
micropython_socket.egg-info/SOURCES.txt
micropython_socket.egg-info/dependency_links.txt
micropython_socket.egg-info/top_level.txt