Metadata-Version: 1.0
Name: micropython-socket
Version: 0.4
Summary: socket module for MicroPython
Home-page: https://github.com/micropython/micropython/issues/405
Author: MicroPython Developers
Author-email: micro-python@googlegroups.com
License: MIT
Platform: UNKNOWN
